mechanics_dsl/__init__.py
mechanics_dsl/cli.py
mechanics_dsl/compiler.py
mechanics_dsl/energy.py
mechanics_dsl/error_handling.py
mechanics_dsl/exceptions.py
mechanics_dsl/logging_config.py
mechanics_dsl/presets.py
mechanics_dsl/protocols.py
mechanics_dsl/py.typed
mechanics_dsl/repl.py
mechanics_dsl/security.py
mechanics_dsl/solver_numba.py
mechanics_dsl/symbolic.py
mechanics_dsl/units.py
mechanics_dsl/validators.py
mechanics_dsl/visualization.py
mechanics_dsl/analysis/__init__.py
mechanics_dsl/analysis/energy.py
mechanics_dsl/analysis/stability.py
mechanics_dsl/backends/__init__.py
mechanics_dsl/backends/base.py
mechanics_dsl/backends/jax_backend.py
mechanics_dsl/codegen/__init__.py
mechanics_dsl/codegen/arduino.py
mechanics_dsl/codegen/arm.py
mechanics_dsl/codegen/base.py
mechanics_dsl/codegen/cpp.py
mechanics_dsl/codegen/cuda.py
mechanics_dsl/codegen/cuda_sph.py
mechanics_dsl/codegen/fortran.py
mechanics_dsl/codegen/javascript.py
mechanics_dsl/codegen/julia.py
mechanics_dsl/codegen/matlab.py
mechanics_dsl/codegen/openmp.py
mechanics_dsl/codegen/python.py
mechanics_dsl/codegen/rust.py
mechanics_dsl/codegen/wasm.py
mechanics_dsl/compiler_pkg/__init__.py
mechanics_dsl/compiler_pkg/particles.py
mechanics_dsl/compiler_pkg/serializer.py
mechanics_dsl/core/__init__.py
mechanics_dsl/domains/__init__.py
mechanics_dsl/domains/base.py
mechanics_dsl/domains/classical/__init__.py
mechanics_dsl/domains/classical/canonical.py
mechanics_dsl/domains/classical/central_forces.py
mechanics_dsl/domains/classical/collisions.py
mechanics_dsl/domains/classical/constraints.py
mechanics_dsl/domains/classical/continuum.py
mechanics_dsl/domains/classical/dissipation.py
mechanics_dsl/domains/classical/hamiltonian.py
mechanics_dsl/domains/classical/lagrangian.py
mechanics_dsl/domains/classical/nonholonomic.py
mechanics_dsl/domains/classical/oscillations.py
mechanics_dsl/domains/classical/perturbation.py
mechanics_dsl/domains/classical/rigidbody.py
mechanics_dsl/domains/classical/scattering.py
mechanicsdsl_core-2.0.6.dist-info/licenses/LICENSE
mechanicsdsl_core-2.0.6.dist-info/METADATA
mechanicsdsl_core-2.0.6.dist-info/WHEEL
mechanicsdsl_core-2.0.6.dist-info/entry_points.txt
mechanicsdsl_core-2.0.6.dist-info/top_level.txt
mechanicsdsl_core-2.0.6.dist-info/RECORD
