Metadata-Version: 2.4
Name: mechanicsdsl-core
Version: 2.0.6
Summary: A Domain-Specific Language and Transpiler for Classical Mechanics
Author-email: Noah Parsons <nomapa223@gmail.com>
License: MIT License
Project-URL: Repository, https://github.com/MechanicsDSL/mechanicsdsl
Project-URL: Documentation, https://mechanicsdsl.readthedocs.io
Project-URL: Bug Tracker, https://github.com/MechanicsDSL/mechanicsdsl/issues
Keywords: physics,simulation,mechanics,dsl,lagrangian,hamiltonian,code-generation,scientific-computing,embedded,raspberry-pi,arm,gpu,cuda
Classifier: Development Status :: 5 - Production/Stable
Classifier: Intended Audience :: Science/Research
Classifier: Intended Audience :: Education
Classifier: Intended Audience :: Developers
Classifier: License :: OSI Approved :: MIT License
Classifier: Operating System :: OS Independent
Classifier: Operating System :: POSIX :: Linux
Classifier: Programming Language :: Python :: 3
Classifier: Programming Language :: Python :: 3.9
Classifier: Programming Language :: Python :: 3.10
Classifier: Programming Language :: Python :: 3.11
Classifier: Programming Language :: Python :: 3.12
Classifier: Programming Language :: Python :: 3.13
Classifier: Programming Language :: Python :: 3.14
Classifier: Programming Language :: C++
Classifier: Programming Language :: Rust
Classifier: Topic :: Scientific/Engineering :: Physics
Classifier: Topic :: Scientific/Engineering :: Mathematics
Classifier: Topic :: Software Development :: Code Generators
Classifier: Topic :: Software Development :: Compilers
Classifier: Topic :: System :: Emulators
Classifier: Topic :: System :: Hardware
Requires-Python: >=3.9
License-File: LICENSE
Requires-Dist: numpy>=1.20.0
Requires-Dist: scipy>=1.7.0
Requires-Dist: sympy>=1.8
Requires-Dist: matplotlib>=3.4.0
Requires-Dist: tqdm>=4.60.0
Provides-Extra: test
Requires-Dist: pytest; extra == "test"
Requires-Dist: pytest-cov; extra == "test"
Requires-Dist: hypothesis>=6.0; extra == "test"
Provides-Extra: codegen
Requires-Dist: pybind11; extra == "codegen"
Provides-Extra: jit
Requires-Dist: numba>=0.56.0; extra == "jit"
Provides-Extra: typing
Requires-Dist: mypy; extra == "typing"
Requires-Dist: types-setuptools; extra == "typing"
Provides-Extra: jax
Requires-Dist: jax>=0.4.0; extra == "jax"
Requires-Dist: jaxlib>=0.4.0; extra == "jax"
Requires-Dist: diffrax>=0.4.0; extra == "jax"
Provides-Extra: jax-gpu
Requires-Dist: jax[cuda12]>=0.4.0; extra == "jax-gpu"
Requires-Dist: diffrax>=0.4.0; extra == "jax-gpu"
Provides-Extra: server
Requires-Dist: fastapi>=0.100.0; extra == "server"
Requires-Dist: uvicorn>=0.22.0; extra == "server"
Requires-Dist: websockets>=11.0; extra == "server"
Provides-Extra: jupyter
Requires-Dist: ipywidgets>=8.0.0; extra == "jupyter"
Requires-Dist: ipython>=8.0.0; extra == "jupyter"
Provides-Extra: lsp
Requires-Dist: pygls>=1.0.0; extra == "lsp"
Requires-Dist: lsprotocol>=2023.0.0; extra == "lsp"
Provides-Extra: openmao
Requires-Dist: openmdao>=3.25.0; extra == "openmao"
Provides-Extra: embedded
Requires-Dist: RPi.GPIO>=0.7.0; (platform_machine == "aarch64" or platform_machine == "armv7l") and extra == "embedded"
Provides-Extra: arm
Requires-Dist: numpy>=1.20.0; extra == "arm"
Provides-Extra: dev
Requires-Dist: pytest; extra == "dev"
Requires-Dist: pytest-cov; extra == "dev"
Requires-Dist: hypothesis>=6.0; extra == "dev"
Requires-Dist: mypy; extra == "dev"
Requires-Dist: types-setuptools; extra == "dev"
Requires-Dist: black; extra == "dev"
Requires-Dist: flake8; extra == "dev"
Requires-Dist: isort; extra == "dev"
Requires-Dist: bandit; extra == "dev"
Provides-Extra: all
Requires-Dist: numba>=0.56.0; extra == "all"
Requires-Dist: pybind11; extra == "all"
Requires-Dist: hypothesis>=6.0; extra == "all"
Requires-Dist: mypy; extra == "all"
Requires-Dist: fastapi>=0.100.0; extra == "all"
Requires-Dist: uvicorn>=0.22.0; extra == "all"
Requires-Dist: ipywidgets>=8.0.0; extra == "all"
Requires-Dist: pygls>=1.0.0; extra == "all"
Dynamic: license-file
